opyls/__init__.py
opyls/collections.py
opyls/dates.py
opyls/json.py
opyls/load.py
opyls/paths.py
opyls-0.0.8.dist-info/LICENSE
opyls-0.0.8.dist-info/METADATA
opyls-0.0.8.dist-info/WHEEL
opyls-0.0.8.dist-info/top_level.txt
opyls-0.0.8.dist-info/RECORD
