Metadata-Version: 2.1
Name: opyls
Version: 0.0.8
Summary: opa_oz's python utils
Author: Vladimir Levin
Author-email: opaozhub@gmail.com
Keywords: python,utils
Classifier: Development Status :: 3 - Alpha
Classifier: Intended Audience :: Education
Classifier: Programming Language :: Python :: 2
Classifier: Programming Language :: Python :: 3
Classifier: Operating System :: MacOS :: MacOS X
Classifier: Operating System :: Microsoft :: Windows
License-File: LICENSE
